{"sections":{"main":{"type":"page-content__main","disabled":true,"settings":{"show_heading":true,"heading_alignment":"left","width":"standard","padding_top":40,"padding_bottom":40,"css_class":"","custom_css":""}},"7d152d7d-51d6-494c-9e35-f5afea869779":{"type":"banner-with-overlap-content","settings":{"link":"","image":"shopify:\/\/shop_images\/Careers_PageArtboard_1.jpg","mobile_image":"shopify:\/\/shop_images\/Careers_PageArtboard_1_copy.jpg","title":"PERKS & BENEFITS","title_text_weight":"bold","subtitle":"","pretext":"<p>DISCOVER ALL THE PERKS, TREATS AND BENEFITS OF  JOINING OUR JO MERCER TEAM <\/p>","content_position":"middle","pretext_color":"#000000","heading_color":"#000000","subheading_color":"#000000","text_alignment":"center","text_horizontal_position":"center","text_vertical_position":"middle","section_background_color":"#000000","background_color":"rgba(255,255,255,1)","background_opacity":100,"border_color":"#ffffff","border_width":0,"text_width":40,"button_1":"","button_1_link":"","button_1_style":"button--secondary","button_2":"","button_2_link":"","button_2_style":"button--secondary","show_scroll_arrow":true,"mobile_image_crop":"none","mobile_text_below_image":true,"pretext_color_mobile":"rgba(0,0,0,0)","heading_color_mobile":"rgba(0,0,0,0)","subheading_color_mobile":"rgba(0,0,0,0)","width":"wide","padding_top":0,"padding_bottom":0,"padding_left":0,"padding_right":0,"animation":"none","css_class":"","custom_css":""}},"342cd5bc-3422-4923-95a5-17d22d4cdc48":{"type":"index__icon-with-text-column","blocks":{"template--14538213195910__342cd5bc-3422-4923-95a5-17d22d4cdc48-16662746730c73a97b-0":{"type":"logo_image","settings":{"icon_label":"","title":"","text":"<p>Very generous shoe discounts<\/p>","button_label":"","link":""}},"template--14538213195910__342cd5bc-3422-4923-95a5-17d22d4cdc48-16662746730c73a97b-1":{"type":"logo_image","settings":{"icon_label":"","title":"","text":"<p>Team based rewards and events<\/p>","button_label":"","link":""}},"template--14538213195910__342cd5bc-3422-4923-95a5-17d22d4cdc48-16662746730c73a97b-2":{"type":"logo_image","settings":{"icon_label":"","title":"","text":"<p>Competitive salary packages<\/p>","button_label":"","link":""}},"template--14538213195910__342cd5bc-3422-4923-95a5-17d22d4cdc48-16662746730c73a97b-3":{"type":"logo_image","settings":{"icon_label":"","title":"","text":"<p>Monthly and Annual Bonuses<\/p>","button_label":"","link":""}},"8b4bd23a-0dc2-4d5b-bb81-78363ec6588f":{"type":"logo_image","settings":{"icon_label":"","title":"","text":"<p>Customer service incentives<\/p>","button_label":"","link":""}},"735f4db1-92e2-42fa-b13d-1021b457759b":{"type":"logo_image","settings":{"icon_label":"","title":"","text":"<p>Career development opportunities<\/p>","button_label":"","link":""}}},"block_order":["template--14538213195910__342cd5bc-3422-4923-95a5-17d22d4cdc48-16662746730c73a97b-0","template--14538213195910__342cd5bc-3422-4923-95a5-17d22d4cdc48-16662746730c73a97b-1","template--14538213195910__342cd5bc-3422-4923-95a5-17d22d4cdc48-16662746730c73a97b-2","template--14538213195910__342cd5bc-3422-4923-95a5-17d22d4cdc48-16662746730c73a97b-3","8b4bd23a-0dc2-4d5b-bb81-78363ec6588f","735f4db1-92e2-42fa-b13d-1021b457759b"],"settings":{"icons_per_row":3,"align_text":"center","icon_size":"medium","button_style":"button--primary","icon_color":"rgba(255,255,255,1)","text_color":"rgba(255,255,255,1)","background":"#000000","gradient":"rgba(0,0,0,0)","gradient_rotation":0,"width":"standard","show_gutter":true,"padding_top":20,"padding_bottom":20,"padding_left":0,"padding_right":0,"animation":"none","css_class":"","custom_css":""}},"6120fdde-9398-4b69-a5f1-39bcce0ed064":{"type":"index__image-with-text","blocks":{"template--14538213195910__6120fdde-9398-4b69-a5f1-39bcce0ed064-166627358188a0dc7a-1":{"type":"image","settings":{"image":"shopify:\/\/shop_images\/Careers_PageArtboard_1_copy_2.jpg","image_link":""}},"template--14538213195910__6120fdde-9398-4b69-a5f1-39bcce0ed064-166627358188a0dc7a-2":{"type":"text","settings":{"title":"OPPORTUNITIES","heading_size":"regular","text":"<p>Join Jo Mercer for a career that supports your skill development, provides valuable experience, and offers mentorship to build your confidence and empower your future. Explore our available opportunities to become part of our talented team.<\/p>","alignment":"left","vertical_position":"center","button_label":"CURRENT OPPORTUNITIES","link":"shopify:\/\/pages\/new-opportunities","button_style":"button--primary","background":"rgba(0,0,0,0)","text_color":"rgba(0,0,0,0)"}}},"block_order":["template--14538213195910__6120fdde-9398-4b69-a5f1-39bcce0ed064-166627358188a0dc7a-1","template--14538213195910__6120fdde-9398-4b69-a5f1-39bcce0ed064-166627358188a0dc7a-2"],"settings":{"width":"standard","show_gutter":true,"padding_top":30,"padding_bottom":30,"animation":"none","mobile_padding_top":25,"mobile_padding_bottom":25,"css_class":"","custom_css":""}}},"order":["main","7d152d7d-51d6-494c-9e35-f5afea869779","342cd5bc-3422-4923-95a5-17d22d4cdc48","6120fdde-9398-4b69-a5f1-39bcce0ed064"]}